via/__init__.py
via/ignore.py
via/license.py
via/utils.py
via-0.1.2.dist-info/LICENSE
via-0.1.2.dist-info/METADATA
via-0.1.2.dist-info/WHEEL
via-0.1.2.dist-info/entry_points.txt
via-0.1.2.dist-info/top_level.txt
via-0.1.2.dist-info/RECORD
