Metadata-Version: 2.1
Name: via
Version: 0.1.2
Summary: initialize your repository
Author-email: Keming <kemingy94@gmail.com>
Project-URL: Homepage, https://github.com/kemingy/via
Classifier: Intended Audience :: Developers
Classifier: Programming Language :: Python :: 3
Classifier: License :: OSI Approved :: MIT License
Classifier: Operating System :: OS Independent
Requires-Python: >=3.6
License-File: LICENSE
Requires-Dist: urllib3 (>=2.0.2)
